{"FL_DATE":"2000-01-31","OP_CARRIER_FL_NUM":930,"ORIGIN_CITY_NAME":"St. Louis, MO","DEST":"FLL","DEST_CITY_NAME":"Fort Lauderdale, FL","CRS_DEP_TIME":2133,"DEP_TIME":2205,"WHEELS_ON":130,"TAXI_IN":5,"CRS_ARR_TIME":111,"ARR_TIME":135,"CANCELLED":0,"DISTANCE":1056}
{"FL_DATE":"2000-01-31","OP_CARRIER_FL_NUM":16,"ORIGIN_CITY_NAME":"St. Louis, MO","DEST":"JFK","DEST_CITY_NAME":"New York, NY","CRS_DEP_TIME":1105,"DEP_TIME":1110,"WHEELS_ON":1413,"TAXI_IN":5,"CRS_ARR_TIME":1421,"ARR_TIME":1418,"CANCELLED":0,"DISTANCE":892}
{"FL_DATE":"2000-01-31","OP_CARRIER_FL_NUM":60,"ORIGIN_CITY_NAME":"St. Louis, MO","DEST":"JFK","DEST_CITY_NAME":"New York, NY","CRS_DEP_TIME":1850,"DEP_TIME":1904,"WHEELS_ON":2229,"TAXI_IN":9,"CRS_ARR_TIME":2213,"ARR_TIME":2238,"CANCELLED":0,"DISTANCE":892}
{"FL_DATE":"2000-01-31","OP_CARRIER_FL_NUM":88,"ORIGIN_CITY_NAME":"St. Louis, MO","DEST":"JFK","DEST_CITY_NAME":"New York, NY","CRS_DEP_TIME":2150,"DEP_TIME":2200,"WHEELS_ON":109,"TAXI_IN":5,"CRS_ARR_TIME":108,"ARR_TIME":114,"CANCELLED":0,"DISTANCE":892}
{"FL_DATE":"2000-01-31","OP_CARRIER_FL_NUM":848,"ORIGIN_CITY_NAME":"St. Louis, MO","DEST":"JFK","DEST_CITY_NAME":"New York, NY","CRS_DEP_TIME":1715,"DEP_TIME":1731,"WHEELS_ON":2044,"TAXI_IN":4,"CRS_ARR_TIME":2040,"ARR_TIME":2048,"CANCELLED":0,"DISTANCE":892}
{"FL_DATE":"2000-01-31","OP_CARRIER_FL_NUM":924,"ORIGIN_CITY_NAME":"St. Louis, MO","DEST":"JFK","DEST_CITY_NAME":"New York, NY","CRS_DEP_TIME":1310,"DEP_TIME":1308,"WHEELS_ON":1626,"TAXI_IN":4,"CRS_ARR_TIME":1637,"ARR_TIME":1630,"CANCELLED":0,"DISTANCE":892}
{"FL_DATE":"2000-01-31","OP_CARRIER_FL_NUM":7,"ORIGIN_CITY_NAME":"St. Louis, MO","DEST":"LAS","DEST_CITY_NAME":"Las Vegas, NV","CRS_DEP_TIME":1815,"DEP_TIME":1903,"WHEELS_ON":2027,"TAXI_IN":7,"CRS_ARR_TIME":1955,"ARR_TIME":2034,"CANCELLED":0,"DISTANCE":1372}
{"FL_DATE":"2000-01-31","OP_CARRIER_FL_NUM":163,"ORIGIN_CITY_NAME":"St. Louis, MO","DEST":"LAS","DEST_CITY_NAME":"Las Vegas, NV","CRS_DEP_TIME":2012,"DEP_TIME":2043,"WHEELS_ON":2204,"TAXI_IN":11,"CRS_ARR_TIME":2144,"ARR_TIME":2215,"CANCELLED":0,"DISTANCE":1372}
{"FL_DATE":"2000-01-31","OP_CARRIER_FL_NUM":417,"ORIGIN_CITY_NAME":"St. Louis, MO","DEST":"LAS","DEST_CITY_NAME":"Las Vegas, NV","CRS_DEP_TIME":1128,"DEP_TIME":1126,"WHEELS_ON":1236,"TAXI_IN":5,"CRS_ARR_TIME":1302,"ARR_TIME":1241,"CANCELLED":0,"DISTANCE":1372}
{"FL_DATE":"2000-01-31","OP_CARRIER_FL_NUM":419,"ORIGIN_CITY_NAME":"St. Louis, MO","DEST":"LAS","DEST_CITY_NAME":"Las Vegas, NV","CRS_DEP_TIME":940,"DEP_TIME":941,"WHEELS_ON":1050,"TAXI_IN":8,"CRS_ARR_TIME":1117,"ARR_TIME":1058,"CANCELLED":0,"DISTANCE":1372}
{"FL_DATE":"2000-01-31","OP_CARRIER_FL_NUM":481,"ORIGIN_CITY_NAME":"St. Louis, MO","DEST":"LAS","DEST_CITY_NAME":"Las Vegas, NV","CRS_DEP_TIME":2300,"DEP_TIME":2259,"WHEELS_ON":1,"TAXI_IN":7,"CRS_ARR_TIME":30,"ARR_TIME":8,"CANCELLED":0,"DISTANCE":1372}
{"FL_DATE":"2000-01-31","OP_CARRIER_FL_NUM":124,"ORIGIN_CITY_NAME":"St. Louis, MO","DEST":"MSP","DEST_CITY_NAME":"Minneapolis, MN","CRS_DEP_TIME":1707,"DEP_TIME":1707,"WHEELS_ON":1834,"TAXI_IN":2,"CRS_ARR_TIME":1841,"ARR_TIME":1836,"CANCELLED":0,"DISTANCE":448}
{"FL_DATE":"2000-01-31","OP_CARRIER_FL_NUM":126,"ORIGIN_CITY_NAME":"St. Louis, MO","DEST":"MSP","DEST_CITY_NAME":"Minneapolis, MN","CRS_DEP_TIME":745,"CRS_ARR_TIME":922,"CANCELLED":1,"DISTANCE":448}
{"FL_DATE":"2000-01-31","OP_CARRIER_FL_NUM":130,"ORIGIN_CITY_NAME":"St. Louis, MO","DEST":"MSP","DEST_CITY_NAME":"Minneapolis, MN","CRS_DEP_TIME":1245,"DEP_TIME":1244,"WHEELS_ON":1412,"TAXI_IN":3,"CRS_ARR_TIME":1418,"ARR_TIME":1415,"CANCELLED":0,"DISTANCE":448}
{"FL_DATE":"2000-01-31","OP_CARRIER_FL_NUM":210,"ORIGIN_CITY_NAME":"St. Louis, MO","DEST":"MSP","DEST_CITY_NAME":"Minneapolis, MN","CRS_DEP_TIME":1410,"DEP_TIME":1406,"WHEELS_ON":1529,"TAXI_IN":6,"CRS_ARR_TIME":1547,"ARR_TIME":1535,"CANCELLED":0,"DISTANCE":448}
{"FL_DATE":"2000-01-31","OP_CARRIER_FL_NUM":331,"ORIGIN_CITY_NAME":"St. Louis, MO","DEST":"MSP","DEST_CITY_NAME":"Minneapolis, MN","CRS_DEP_TIME":1833,"DEP_TIME":1831,"WHEELS_ON":2006,"TAXI_IN":4,"CRS_ARR_TIME":2012,"ARR_TIME":2010,"CANCELLED":0,"DISTANCE":448}
{"FL_DATE":"2000-01-31","OP_CARRIER_FL_NUM":391,"ORIGIN_CITY_NAME":"St. Louis, MO","DEST":"MSP","DEST_CITY_NAME":"Minneapolis, MN","CRS_DEP_TIME":2230,"DEP_TIME":2227,"WHEELS_ON":2351,"TAXI_IN":3,"CRS_ARR_TIME":2359,"ARR_TIME":2354,"CANCELLED":0,"DISTANCE":448}
{"FL_DATE":"2000-01-31","OP_CARRIER_FL_NUM":507,"ORIGIN_CITY_NAME":"St. Louis, MO","DEST":"MSP","DEST_CITY_NAME":"Minneapolis, MN","CRS_DEP_TIME":1116,"DEP_TIME":1116,"WHEELS_ON":1240,"TAXI_IN":4,"CRS_ARR_TIME":1250,"ARR_TIME":1244,"CANCELLED":0,"DISTANCE":448}
{"FL_DATE":"2000-01-31","OP_CARRIER_FL_NUM":591,"ORIGIN_CITY_NAME":"St. Louis, MO","DEST":"MSP","DEST_CITY_NAME":"Minneapolis, MN","CRS_DEP_TIME":848,"DEP_TIME":847,"WHEELS_ON":1027,"TAXI_IN":4,"CRS_ARR_TIME":1030,"ARR_TIME":1031,"CANCELLED":0,"DISTANCE":448}
{"FL_DATE":"2000-01-31","OP_CARRIER_FL_NUM":693,"ORIGIN_CITY_NAME":"St. Louis, MO","DEST":"MSP","DEST_CITY_NAME":"Minneapolis, MN","CRS_DEP_TIME":1538,"DEP_TIME":1534,"WHEELS_ON":1659,"TAXI_IN":3,"CRS_ARR_TIME":1719,"ARR_TIME":1702,"CANCELLED":0,"DISTANCE":448}
{"FL_DATE":"2000-01-31","OP_CARRIER_FL_NUM":694,"ORIGIN_CITY_NAME":"St. Louis, MO","DEST":"MSP","DEST_CITY_NAME":"Minneapolis, MN","CRS_DEP_TIME":2011,"DEP_TIME":2011,"WHEELS_ON":2146,"TAXI_IN":4,"CRS_ARR_TIME":2147,"ARR_TIME":2150,"CANCELLED":0,"DISTANCE":448}
{"FL_DATE":"2000-01-31","OP_CARRIER_FL_NUM":455,"ORIGIN_CITY_NAME":"St. Louis, MO","DEST":"OMA","DEST_CITY_NAME":"Omaha, NE","CRS_DEP_TIME":2244,"DEP_TIME":53,"WHEELS_ON":158,"TAXI_IN":3,"CRS_ARR_TIME":2359,"ARR_TIME":201,"CANCELLED":0,"DISTANCE":342}
{"FL_DATE":"2000-01-31","OP_CARRIER_FL_NUM":467,"ORIGIN_CITY_NAME":"St. Louis, MO","DEST":"OMA","DEST_CITY_NAME":"Omaha, NE","CRS_DEP_TIME":1418,"DEP_TIME":1417,"WHEELS_ON":1523,"TAXI_IN":4,"CRS_ARR_TIME":1537,"ARR_TIME":1527,"CANCELLED":0,"DISTANCE":342}
{"FL_DATE":"2000-01-31","OP_CARRIER_FL_NUM":469,"ORIGIN_CITY_NAME":"St. Louis, MO","DEST":"OMA","DEST_CITY_NAME":"Omaha, NE","CRS_DEP_TIME":1122,"DEP_TIME":1122,"WHEELS_ON":1249,"TAXI_IN":4,"CRS_ARR_TIME":1238,"ARR_TIME":1253,"CANCELLED":0,"DISTANCE":342}
{"FL_DATE":"2000-01-31","OP_CARRIER_FL_NUM":487,"ORIGIN_CITY_NAME":"St. Louis, MO","DEST":"OMA","DEST_CITY_NAME":"Omaha, NE","CRS_DEP_TIME":2033,"DEP_TIME":2033,"WHEELS_ON":2200,"TAXI_IN":4,"CRS_ARR_TIME":2200,"ARR_TIME":2204,"CANCELLED":0,"DISTANCE":342}
{"FL_DATE":"2000-01-31","OP_CARRIER_FL_NUM":525,"ORIGIN_CITY_NAME":"St. Louis, MO","DEST":"OMA","DEST_CITY_NAME":"Omaha, NE","CRS_DEP_TIME":850,"CRS_ARR_TIME":1012,"CANCELLED":1,"DISTANCE":342}
{"FL_DATE":"2000-01-31","OP_CARRIER_FL_NUM":577,"ORIGIN_CITY_NAME":"St. Louis, MO","DEST":"OMA","DEST_CITY_NAME":"Omaha, NE","CRS_DEP_TIME":1717,"DEP_TIME":1719,"WHEELS_ON":1826,"TAXI_IN":3,"CRS_ARR_TIME":1842,"ARR_TIME":1829,"CANCELLED":0,"DISTANCE":342}
{"FL_DATE":"2000-01-31","OP_CARRIER_FL_NUM":221,"ORIGIN_CITY_NAME":"St. Louis, MO","DEST":"ONT","DEST_CITY_NAME":"Ontario, CA","CRS_DEP_TIME":853,"DEP_TIME":852,"WHEELS_ON":1054,"TAXI_IN":4,"CRS_ARR_TIME":1100,"ARR_TIME":1058,"CANCELLED":0,"DISTANCE":1546}
{"FL_DATE":"2000-01-31","OP_CARRIER_FL_NUM":407,"ORIGIN_CITY_NAME":"St. Louis, MO","DEST":"ONT","DEST_CITY_NAME":"Ontario, CA","CRS_DEP_TIME":1722,"DEP_TIME":1726,"WHEELS_ON":1914,"TAXI_IN":2,"CRS_ARR_TIME":1928,"ARR_TIME":1916,"CANCELLED":0,"DISTANCE":1546}
{"FL_DATE":"2000-01-31","OP_CARRIER_FL_NUM":562,"ORIGIN_CITY_NAME":"St. Louis, MO","DEST":"RDU","DEST_CITY_NAME":"Raleigh/Durham, NC","CRS_DEP_TIME":1315,"DEP_TIME":1315,"WHEELS_ON":1610,"TAXI_IN":7,"CRS_ARR_TIME":1612,"ARR_TIME":1617,"CANCELLED":0,"DISTANCE":667}
{"FL_DATE":"2000-01-31","OP_CARRIER_FL_NUM":582,"ORIGIN_CITY_NAME":"St. Louis, MO","DEST":"RDU","DEST_CITY_NAME":"Raleigh/Durham, NC","CRS_DEP_TIME":1020,"DEP_TIME":1020,"WHEELS_ON":1304,"TAXI_IN":4,"CRS_ARR_TIME":1313,"ARR_TIME":1308,"CANCELLED":0,"DISTANCE":667}
{"FL_DATE":"2000-01-31","OP_CARRIER_FL_NUM":594,"ORIGIN_CITY_NAME":"St. Louis, MO","DEST":"RDU","DEST_CITY_NAME":"Raleigh/Durham, NC","CRS_DEP_TIME":1850,"DEP_TIME":1850,"WHEELS_ON":2150,"TAXI_IN":3,"CRS_ARR_TIME":2148,"ARR_TIME":2153,"CANCELLED":0,"DISTANCE":667}
{"FL_DATE":"2000-01-31","OP_CARRIER_FL_NUM":610,"ORIGIN_CITY_NAME":"St. Louis, MO","DEST":"RDU","DEST_CITY_NAME":"Raleigh/Durham, NC","CRS_DEP_TIME":2135,"DEP_TIME":2207,"WHEELS_ON":52,"TAXI_IN":3,"CRS_ARR_TIME":20,"ARR_TIME":55,"CANCELLED":0,"DISTANCE":667}
{"FL_DATE":"2000-01-31","OP_CARRIER_FL_NUM":274,"ORIGIN_CITY_NAME":"St. Louis, MO","DEST":"SDF","DEST_CITY_NAME":"Louisville, KY","CRS_DEP_TIME":2145,"DEP_TIME":2151,"WHEELS_ON":2353,"TAXI_IN":4,"CRS_ARR_TIME":2350,"ARR_TIME":2357,"CANCELLED":0,"DISTANCE":254}
{"FL_DATE":"2000-01-31","OP_CARRIER_FL_NUM":292,"ORIGIN_CITY_NAME":"St. Louis, MO","DEST":"SDF","DEST_CITY_NAME":"Louisville, KY","CRS_DEP_TIME":1300,"DEP_TIME":1259,"WHEELS_ON":1449,"TAXI_IN":3,"CRS_ARR_TIME":1509,"ARR_TIME":1452,"CANCELLED":0,"DISTANCE":254}
{"FL_DATE":"2000-01-31","OP_CARRIER_FL_NUM":354,"ORIGIN_CITY_NAME":"St. Louis, MO","DEST":"SDF","DEST_CITY_NAME":"Louisville, KY","CRS_DEP_TIME":1552,"DEP_TIME":1557,"WHEELS_ON":1757,"TAXI_IN":4,"CRS_ARR_TIME":1801,"ARR_TIME":1801,"CANCELLED":0,"DISTANCE":254}
{"FL_DATE":"2000-01-31","OP_CARRIER_FL_NUM":734,"ORIGIN_CITY_NAME":"St. Louis, MO","DEST":"SDF","DEST_CITY_NAME":"Louisville, KY","CRS_DEP_TIME":1004,"DEP_TIME":1004,"WHEELS_ON":1156,"TAXI_IN":6,"CRS_ARR_TIME":1207,"ARR_TIME":1202,"CANCELLED":0,"DISTANCE":254}
{"FL_DATE":"2000-01-31","OP_CARRIER_FL_NUM":748,"ORIGIN_CITY_NAME":"St. Louis, MO","DEST":"SDF","DEST_CITY_NAME":"Louisville, KY","CRS_DEP_TIME":1845,"DEP_TIME":1849,"WHEELS_ON":2044,"TAXI_IN":4,"CRS_ARR_TIME":2055,"ARR_TIME":2048,"CANCELLED":0,"DISTANCE":254}
{"FL_DATE":"2000-01-31","OP_CARRIER_FL_NUM":61,"ORIGIN_CITY_NAME":"St. Louis, MO","DEST":"SFO","DEST_CITY_NAME":"San Francisco, CA","CRS_DEP_TIME":2230,"DEP_TIME":2234,"WHEELS_ON":27,"TAXI_IN":3,"CRS_ARR_TIME":58,"ARR_TIME":30,"CANCELLED":0,"DISTANCE":1736}
{"FL_DATE":"2000-01-31","OP_CARRIER_FL_NUM":167,"ORIGIN_CITY_NAME":"St. Louis, MO","DEST":"SFO","DEST_CITY_NAME":"San Francisco, CA","CRS_DEP_TIME":2045,"DEP_TIME":2113,"WHEELS_ON":2340,"TAXI_IN":4,"CRS_ARR_TIME":2316,"ARR_TIME":2344,"CANCELLED":0,"DISTANCE":1736}
{"FL_DATE":"2000-01-31","OP_CARRIER_FL_NUM":175,"ORIGIN_CITY_NAME":"St. Louis, MO","DEST":"SFO","DEST_CITY_NAME":"San Francisco, CA","CRS_DEP_TIME":1715,"DEP_TIME":1716,"WHEELS_ON":1929,"TAXI_IN":5,"CRS_ARR_TIME":1946,"ARR_TIME":1934,"CANCELLED":0,"DISTANCE":1736}
{"FL_DATE":"2000-01-31","OP_CARRIER_FL_NUM":177,"ORIGIN_CITY_NAME":"St. Louis, MO","DEST":"SFO","DEST_CITY_NAME":"San Francisco, CA","CRS_DEP_TIME":1130,"DEP_TIME":1242,"WHEELS_ON":1505,"TAXI_IN":5,"CRS_ARR_TIME":1355,"ARR_TIME":1510,"CANCELLED":0,"DISTANCE":1736}
{"FL_DATE":"2000-01-31","OP_CARRIER_FL_NUM":223,"ORIGIN_CITY_NAME":"St. Louis, MO","DEST":"SFO","DEST_CITY_NAME":"San Francisco, CA","CRS_DEP_TIME":838,"DEP_TIME":840,"WHEELS_ON":1046,"TAXI_IN":6,"CRS_ARR_TIME":1102,"ARR_TIME":1052,"CANCELLED":0,"DISTANCE":1736}
{"FL_DATE":"2000-01-31","OP_CARRIER_FL_NUM":313,"ORIGIN_CITY_NAME":"St. Louis, MO","DEST":"SGF","DEST_CITY_NAME":"Springfield, MO","CRS_DEP_TIME":900,"DEP_TIME":858,"WHEELS_ON":1003,"TAXI_IN":4,"CRS_ARR_TIME":1007,"ARR_TIME":1007,"CANCELLED":0,"DISTANCE":195}
{"FL_DATE":"2000-01-31","OP_CARRIER_FL_NUM":363,"ORIGIN_CITY_NAME":"St. Louis, MO","DEST":"SGF","DEST_CITY_NAME":"Springfield, MO","CRS_DEP_TIME":1430,"DEP_TIME":1431,"WHEELS_ON":1515,"TAXI_IN":3,"CRS_ARR_TIME":1533,"ARR_TIME":1518,"CANCELLED":0,"DISTANCE":195}
{"FL_DATE":"2000-01-31","OP_CARRIER_FL_NUM":517,"ORIGIN_CITY_NAME":"St. Louis, MO","DEST":"SGF","DEST_CITY_NAME":"Springfield, MO","CRS_DEP_TIME":2027,"DEP_TIME":2025,"WHEELS_ON":2121,"TAXI_IN":2,"CRS_ARR_TIME":2132,"ARR_TIME":2123,"CANCELLED":0,"DISTANCE":195}
{"FL_DATE":"2000-01-31","OP_CARRIER_FL_NUM":625,"ORIGIN_CITY_NAME":"St. Louis, MO","DEST":"SGF","DEST_CITY_NAME":"Springfield, MO","CRS_DEP_TIME":2235,"DEP_TIME":2231,"WHEELS_ON":2316,"TAXI_IN":3,"CRS_ARR_TIME":2332,"ARR_TIME":2319,"CANCELLED":0,"DISTANCE":195}
{"FL_DATE":"2000-01-31","OP_CARRIER_FL_NUM":627,"ORIGIN_CITY_NAME":"St. Louis, MO","DEST":"SGF","DEST_CITY_NAME":"Springfield, MO","CRS_DEP_TIME":1146,"DEP_TIME":1145,"WHEELS_ON":1230,"TAXI_IN":3,"CRS_ARR_TIME":1251,"ARR_TIME":1233,"CANCELLED":0,"DISTANCE":195}
{"FL_DATE":"2000-01-31","OP_CARRIER_FL_NUM":691,"ORIGIN_CITY_NAME":"St. Louis, MO","DEST":"SGF","DEST_CITY_NAME":"Springfield, MO","CRS_DEP_TIME":1730,"DEP_TIME":1730,"WHEELS_ON":1841,"TAXI_IN":2,"CRS_ARR_TIME":1840,"ARR_TIME":1843,"CANCELLED":0,"DISTANCE":195}
{"FL_DATE":"2000-01-31","OP_CARRIER_FL_NUM":471,"ORIGIN_CITY_NAME":"St. Louis, MO","DEST":"SHV","DEST_CITY_NAME":"Shreveport, LA","CRS_DEP_TIME":1410,"DEP_TIME":1409,"WHEELS_ON":1530,"TAXI_IN":4,"CRS_ARR_TIME":1547,"ARR_TIME":1534,"CANCELLED":0,"DISTANCE":476}
{"FL_DATE":"2000-01-31","OP_CARRIER_FL_NUM":477,"ORIGIN_CITY_NAME":"St. Louis, MO","DEST":"SHV","DEST_CITY_NAME":"Shreveport, LA","CRS_DEP_TIME":838,"DEP_TIME":836,"WHEELS_ON":1004,"TAXI_IN":5,"CRS_ARR_TIME":1014,"ARR_TIME":1009,"CANCELLED":0,"DISTANCE":476}
{"FL_DATE":"2000-01-31","OP_CARRIER_FL_NUM":483,"ORIGIN_CITY_NAME":"St. Louis, MO","DEST":"SHV","DEST_CITY_NAME":"Shreveport, LA","CRS_DEP_TIME":2025,"CRS_ARR_TIME":2207,"CANCELLED":1,"DISTANCE":476}
{"FL_DATE":"2000-01-31","OP_CARRIER_FL_NUM":204,"ORIGIN_CITY_NAME":"St. Louis, MO","DEST":"TPA","DEST_CITY_NAME":"Tampa, FL","CRS_DEP_TIME":1849,"DEP_TIME":1848,"WHEELS_ON":2211,"TAXI_IN":4,"CRS_ARR_TIME":2214,"ARR_TIME":2215,"CANCELLED":0,"DISTANCE":869}
{"FL_DATE":"2000-01-31","OP_CARRIER_FL_NUM":226,"ORIGIN_CITY_NAME":"St. Louis, MO","DEST":"TPA","DEST_CITY_NAME":"Tampa, FL","CRS_DEP_TIME":1020,"DEP_TIME":1020,"WHEELS_ON":1336,"TAXI_IN":3,"CRS_ARR_TIME":1341,"ARR_TIME":1339,"CANCELLED":0,"DISTANCE":869}
{"FL_DATE":"2000-01-31","OP_CARRIER_FL_NUM":348,"ORIGIN_CITY_NAME":"St. Louis, MO","DEST":"TPA","DEST_CITY_NAME":"Tampa, FL","CRS_DEP_TIME":2133,"DEP_TIME":2132,"WHEELS_ON":36,"TAXI_IN":3,"CRS_ARR_TIME":47,"ARR_TIME":39,"CANCELLED":0,"DISTANCE":869}
{"FL_DATE":"2000-01-31","OP_CARRIER_FL_NUM":422,"ORIGIN_CITY_NAME":"St. Louis, MO","DEST":"TPA","DEST_CITY_NAME":"Tampa, FL","CRS_DEP_TIME":1330,"DEP_TIME":1330,"WHEELS_ON":1650,"TAXI_IN":4,"CRS_ARR_TIME":1647,"ARR_TIME":1654,"CANCELLED":0,"DISTANCE":869}
{"FL_DATE":"2000-01-31","OP_CARRIER_FL_NUM":698,"ORIGIN_CITY_NAME":"St. Louis, MO","DEST":"TPA","DEST_CITY_NAME":"Tampa, FL","CRS_DEP_TIME":750,"DEP_TIME":756,"WHEELS_ON":1112,"TAXI_IN":6,"CRS_ARR_TIME":1110,"ARR_TIME":1118,"CANCELLED":0,"DISTANCE":869}
