{"FL_DATE":"2000-01-01","OP_CARRIER_FL_NUM":415,"ORIGIN_CITY_NAME":"Knoxville, TN","DEST":"STL","DEST_CITY_NAME":"St. Louis, MO","CRS_DEP_TIME":1602,"DEP_TIME":1558,"WHEELS_ON":1618,"TAXI_IN":4,"CRS_ARR_TIME":1634,"ARR_TIME":1622,"CANCELLED":0,"DISTANCE":405}
{"FL_DATE":"2000-01-01","OP_CARRIER_FL_NUM":510,"ORIGIN_CITY_NAME":"Knoxville, TN","DEST":"STL","DEST_CITY_NAME":"St. Louis, MO","CRS_DEP_TIME":1014,"DEP_TIME":1012,"WHEELS_ON":1029,"TAXI_IN":4,"CRS_ARR_TIME":1046,"ARR_TIME":1033,"CANCELLED":0,"DISTANCE":405}
{"FL_DATE":"2000-01-02","OP_CARRIER_FL_NUM":415,"ORIGIN_CITY_NAME":"Knoxville, TN","DEST":"STL","DEST_CITY_NAME":"St. Louis, MO","CRS_DEP_TIME":1602,"DEP_TIME":1600,"WHEELS_ON":1621,"TAXI_IN":5,"CRS_ARR_TIME":1634,"ARR_TIME":1626,"CANCELLED":0,"DISTANCE":405}
{"FL_DATE":"2000-01-02","OP_CARRIER_FL_NUM":510,"ORIGIN_CITY_NAME":"Knoxville, TN","DEST":"STL","DEST_CITY_NAME":"St. Louis, MO","CRS_DEP_TIME":1014,"DEP_TIME":1015,"WHEELS_ON":1038,"TAXI_IN":6,"CRS_ARR_TIME":1046,"ARR_TIME":1044,"CANCELLED":0,"DISTANCE":405}
{"FL_DATE":"2000-01-03","OP_CARRIER_FL_NUM":415,"ORIGIN_CITY_NAME":"Knoxville, TN","DEST":"STL","DEST_CITY_NAME":"St. Louis, MO","CRS_DEP_TIME":1602,"DEP_TIME":1711,"WHEELS_ON":1739,"TAXI_IN":5,"CRS_ARR_TIME":1634,"ARR_TIME":1744,"CANCELLED":0,"DISTANCE":405}
{"FL_DATE":"2000-01-03","OP_CARRIER_FL_NUM":477,"ORIGIN_CITY_NAME":"Knoxville, TN","DEST":"STL","DEST_CITY_NAME":"St. Louis, MO","CRS_DEP_TIME":728,"CRS_ARR_TIME":758,"CANCELLED":1,"DISTANCE":405}
{"FL_DATE":"2000-01-03","OP_CARRIER_FL_NUM":510,"ORIGIN_CITY_NAME":"Knoxville, TN","DEST":"STL","DEST_CITY_NAME":"St. Louis, MO","CRS_DEP_TIME":1014,"DEP_TIME":1122,"WHEELS_ON":1150,"TAXI_IN":6,"CRS_ARR_TIME":1046,"ARR_TIME":1156,"CANCELLED":0,"DISTANCE":405}
{"FL_DATE":"2000-01-04","OP_CARRIER_FL_NUM":415,"ORIGIN_CITY_NAME":"Knoxville, TN","DEST":"STL","DEST_CITY_NAME":"St. Louis, MO","CRS_DEP_TIME":1602,"DEP_TIME":1556,"WHEELS_ON":1633,"TAXI_IN":5,"CRS_ARR_TIME":1634,"ARR_TIME":1638,"CANCELLED":0,"DISTANCE":405}
{"FL_DATE":"2000-01-04","OP_CARRIER_FL_NUM":477,"ORIGIN_CITY_NAME":"Knoxville, TN","DEST":"STL","DEST_CITY_NAME":"St. Louis, MO","CRS_DEP_TIME":728,"DEP_TIME":726,"WHEELS_ON":753,"TAXI_IN":6,"CRS_ARR_TIME":758,"ARR_TIME":759,"CANCELLED":0,"DISTANCE":405}
{"FL_DATE":"2000-01-04","OP_CARRIER_FL_NUM":510,"ORIGIN_CITY_NAME":"Knoxville, TN","DEST":"STL","DEST_CITY_NAME":"St. Louis, MO","CRS_DEP_TIME":1014,"DEP_TIME":1010,"WHEELS_ON":1039,"TAXI_IN":8,"CRS_ARR_TIME":1046,"ARR_TIME":1047,"CANCELLED":0,"DISTANCE":405}
{"FL_DATE":"2000-01-05","OP_CARRIER_FL_NUM":415,"ORIGIN_CITY_NAME":"Knoxville, TN","DEST":"STL","DEST_CITY_NAME":"St. Louis, MO","CRS_DEP_TIME":1602,"DEP_TIME":1559,"WHEELS_ON":1629,"TAXI_IN":4,"CRS_ARR_TIME":1634,"ARR_TIME":1633,"CANCELLED":0,"DISTANCE":405}
{"FL_DATE":"2000-01-05","OP_CARRIER_FL_NUM":477,"ORIGIN_CITY_NAME":"Knoxville, TN","DEST":"STL","DEST_CITY_NAME":"St. Louis, MO","CRS_DEP_TIME":728,"DEP_TIME":725,"WHEELS_ON":740,"TAXI_IN":6,"CRS_ARR_TIME":758,"ARR_TIME":746,"CANCELLED":0,"DISTANCE":405}
{"FL_DATE":"2000-01-05","OP_CARRIER_FL_NUM":510,"ORIGIN_CITY_NAME":"Knoxville, TN","DEST":"STL","DEST_CITY_NAME":"St. Louis, MO","CRS_DEP_TIME":1014,"DEP_TIME":1012,"WHEELS_ON":1026,"TAXI_IN":4,"CRS_ARR_TIME":1046,"ARR_TIME":1030,"CANCELLED":0,"DISTANCE":405}
{"FL_DATE":"2000-01-06","OP_CARRIER_FL_NUM":415,"ORIGIN_CITY_NAME":"Knoxville, TN","DEST":"STL","DEST_CITY_NAME":"St. Louis, MO","CRS_DEP_TIME":1602,"DEP_TIME":1559,"WHEELS_ON":1616,"TAXI_IN":6,"CRS_ARR_TIME":1634,"ARR_TIME":1622,"CANCELLED":0,"DISTANCE":405}
{"FL_DATE":"2000-01-06","OP_CARRIER_FL_NUM":477,"ORIGIN_CITY_NAME":"Knoxville, TN","DEST":"STL","DEST_CITY_NAME":"St. Louis, MO","CRS_DEP_TIME":728,"DEP_TIME":725,"WHEELS_ON":745,"TAXI_IN":7,"CRS_ARR_TIME":758,"ARR_TIME":752,"CANCELLED":0,"DISTANCE":405}
{"FL_DATE":"2000-01-06","OP_CARRIER_FL_NUM":510,"ORIGIN_CITY_NAME":"Knoxville, TN","DEST":"STL","DEST_CITY_NAME":"St. Louis, MO","CRS_DEP_TIME":1014,"DEP_TIME":1013,"WHEELS_ON":1029,"TAXI_IN":5,"CRS_ARR_TIME":1046,"ARR_TIME":1034,"CANCELLED":0,"DISTANCE":405}
{"FL_DATE":"2000-01-07","OP_CARRIER_FL_NUM":415,"ORIGIN_CITY_NAME":"Knoxville, TN","DEST":"STL","DEST_CITY_NAME":"St. Louis, MO","CRS_DEP_TIME":1602,"DEP_TIME":1559,"WHEELS_ON":1623,"TAXI_IN":7,"CRS_ARR_TIME":1634,"ARR_TIME":1630,"CANCELLED":0,"DISTANCE":405}
{"FL_DATE":"2000-01-07","OP_CARRIER_FL_NUM":477,"ORIGIN_CITY_NAME":"Knoxville, TN","DEST":"STL","DEST_CITY_NAME":"St. Louis, MO","CRS_DEP_TIME":728,"DEP_TIME":726,"WHEELS_ON":757,"TAXI_IN":6,"CRS_ARR_TIME":758,"ARR_TIME":803,"CANCELLED":0,"DISTANCE":405}
{"FL_DATE":"2000-01-07","OP_CARRIER_FL_NUM":510,"ORIGIN_CITY_NAME":"Knoxville, TN","DEST":"STL","DEST_CITY_NAME":"St. Louis, MO","CRS_DEP_TIME":1014,"DEP_TIME":1011,"WHEELS_ON":1037,"TAXI_IN":4,"CRS_ARR_TIME":1046,"ARR_TIME":1041,"CANCELLED":0,"DISTANCE":405}
{"FL_DATE":"2000-01-08","OP_CARRIER_FL_NUM":415,"ORIGIN_CITY_NAME":"Knoxville, TN","DEST":"STL","DEST_CITY_NAME":"St. Louis, MO","CRS_DEP_TIME":1602,"DEP_TIME":1557,"WHEELS_ON":1620,"TAXI_IN":6,"CRS_ARR_TIME":1634,"ARR_TIME":1626,"CANCELLED":0,"DISTANCE":405}
{"FL_DATE":"2000-01-08","OP_CARRIER_FL_NUM":477,"ORIGIN_CITY_NAME":"Knoxville, TN","DEST":"STL","DEST_CITY_NAME":"St. Louis, MO","CRS_DEP_TIME":728,"DEP_TIME":725,"WHEELS_ON":753,"TAXI_IN":4,"CRS_ARR_TIME":758,"ARR_TIME":757,"CANCELLED":0,"DISTANCE":405}
{"FL_DATE":"2000-01-08","OP_CARRIER_FL_NUM":510,"ORIGIN_CITY_NAME":"Knoxville, TN","DEST":"STL","DEST_CITY_NAME":"St. Louis, MO","CRS_DEP_TIME":1014,"DEP_TIME":1010,"WHEELS_ON":1043,"TAXI_IN":4,"CRS_ARR_TIME":1046,"ARR_TIME":1047,"CANCELLED":0,"DISTANCE":405}
{"FL_DATE":"2000-01-09","OP_CARRIER_FL_NUM":415,"ORIGIN_CITY_NAME":"Knoxville, TN","DEST":"STL","DEST_CITY_NAME":"St. Louis, MO","CRS_DEP_TIME":1602,"DEP_TIME":1607,"WHEELS_ON":1632,"TAXI_IN":4,"CRS_ARR_TIME":1634,"ARR_TIME":1636,"CANCELLED":0,"DISTANCE":405}
{"FL_DATE":"2000-01-09","OP_CARRIER_FL_NUM":510,"ORIGIN_CITY_NAME":"Knoxville, TN","DEST":"STL","DEST_CITY_NAME":"St. Louis, MO","CRS_DEP_TIME":1014,"DEP_TIME":1012,"WHEELS_ON":1043,"TAXI_IN":3,"CRS_ARR_TIME":1046,"ARR_TIME":1046,"CANCELLED":0,"DISTANCE":405}
{"FL_DATE":"2000-01-10","OP_CARRIER_FL_NUM":415,"ORIGIN_CITY_NAME":"Knoxville, TN","DEST":"STL","DEST_CITY_NAME":"St. Louis, MO","CRS_DEP_TIME":1602,"DEP_TIME":1600,"WHEELS_ON":1630,"TAXI_IN":5,"CRS_ARR_TIME":1634,"ARR_TIME":1635,"CANCELLED":0,"DISTANCE":405}
{"FL_DATE":"2000-01-10","OP_CARRIER_FL_NUM":647,"ORIGIN_CITY_NAME":"Knoxville, TN","DEST":"STL","DEST_CITY_NAME":"St. Louis, MO","CRS_DEP_TIME":728,"DEP_TIME":726,"WHEELS_ON":751,"TAXI_IN":7,"CRS_ARR_TIME":758,"ARR_TIME":758,"CANCELLED":0,"DISTANCE":405}
{"FL_DATE":"2000-01-11","OP_CARRIER_FL_NUM":415,"ORIGIN_CITY_NAME":"Knoxville, TN","DEST":"STL","DEST_CITY_NAME":"St. Louis, MO","CRS_DEP_TIME":1602,"DEP_TIME":1557,"WHEELS_ON":1629,"TAXI_IN":6,"CRS_ARR_TIME":1634,"ARR_TIME":1635,"CANCELLED":0,"DISTANCE":405}
{"FL_DATE":"2000-01-11","OP_CARRIER_FL_NUM":647,"ORIGIN_CITY_NAME":"Knoxville, TN","DEST":"STL","DEST_CITY_NAME":"St. Louis, MO","CRS_DEP_TIME":728,"DEP_TIME":724,"WHEELS_ON":754,"TAXI_IN":5,"CRS_ARR_TIME":758,"ARR_TIME":759,"CANCELLED":0,"DISTANCE":405}
{"FL_DATE":"2000-01-12","OP_CARRIER_FL_NUM":415,"ORIGIN_CITY_NAME":"Knoxville, TN","DEST":"STL","DEST_CITY_NAME":"St. Louis, MO","CRS_DEP_TIME":1602,"DEP_TIME":1601,"WHEELS_ON":1626,"TAXI_IN":5,"CRS_ARR_TIME":1634,"ARR_TIME":1631,"CANCELLED":0,"DISTANCE":405}
{"FL_DATE":"2000-01-12","OP_CARRIER_FL_NUM":647,"ORIGIN_CITY_NAME":"Knoxville, TN","DEST":"STL","DEST_CITY_NAME":"St. Louis, MO","CRS_DEP_TIME":728,"DEP_TIME":726,"WHEELS_ON":750,"TAXI_IN":4,"CRS_ARR_TIME":758,"ARR_TIME":754,"CANCELLED":0,"DISTANCE":405}
{"FL_DATE":"2000-01-13","OP_CARRIER_FL_NUM":415,"ORIGIN_CITY_NAME":"Knoxville, TN","DEST":"STL","DEST_CITY_NAME":"St. Louis, MO","CRS_DEP_TIME":1602,"DEP_TIME":1601,"WHEELS_ON":1634,"TAXI_IN":5,"CRS_ARR_TIME":1634,"ARR_TIME":1639,"CANCELLED":0,"DISTANCE":405}
{"FL_DATE":"2000-01-13","OP_CARRIER_FL_NUM":647,"ORIGIN_CITY_NAME":"Knoxville, TN","DEST":"STL","DEST_CITY_NAME":"St. Louis, MO","CRS_DEP_TIME":728,"DEP_TIME":727,"WHEELS_ON":753,"TAXI_IN":4,"CRS_ARR_TIME":758,"ARR_TIME":757,"CANCELLED":0,"DISTANCE":405}
{"FL_DATE":"2000-01-14","OP_CARRIER_FL_NUM":415,"ORIGIN_CITY_NAME":"Knoxville, TN","DEST":"STL","DEST_CITY_NAME":"St. Louis, MO","CRS_DEP_TIME":1602,"DEP_TIME":1559,"WHEELS_ON":1634,"TAXI_IN":4,"CRS_ARR_TIME":1634,"ARR_TIME":1638,"CANCELLED":0,"DISTANCE":405}
{"FL_DATE":"2000-01-14","OP_CARRIER_FL_NUM":647,"ORIGIN_CITY_NAME":"Knoxville, TN","DEST":"STL","DEST_CITY_NAME":"St. Louis, MO","CRS_DEP_TIME":728,"DEP_TIME":726,"WHEELS_ON":802,"TAXI_IN":6,"CRS_ARR_TIME":758,"ARR_TIME":808,"CANCELLED":0,"DISTANCE":405}
{"FL_DATE":"2000-01-15","OP_CARRIER_FL_NUM":415,"ORIGIN_CITY_NAME":"Knoxville, TN","DEST":"STL","DEST_CITY_NAME":"St. Louis, MO","CRS_DEP_TIME":1602,"DEP_TIME":1556,"WHEELS_ON":1616,"TAXI_IN":6,"CRS_ARR_TIME":1634,"ARR_TIME":1622,"CANCELLED":0,"DISTANCE":405}
{"FL_DATE":"2000-01-15","OP_CARRIER_FL_NUM":647,"ORIGIN_CITY_NAME":"Knoxville, TN","DEST":"STL","DEST_CITY_NAME":"St. Louis, MO","CRS_DEP_TIME":728,"DEP_TIME":725,"WHEELS_ON":756,"TAXI_IN":4,"CRS_ARR_TIME":758,"ARR_TIME":800,"CANCELLED":0,"DISTANCE":405}
{"FL_DATE":"2000-01-16","OP_CARRIER_FL_NUM":415,"ORIGIN_CITY_NAME":"Knoxville, TN","DEST":"STL","DEST_CITY_NAME":"St. Louis, MO","CRS_DEP_TIME":1602,"DEP_TIME":1556,"WHEELS_ON":1614,"TAXI_IN":4,"CRS_ARR_TIME":1634,"ARR_TIME":1618,"CANCELLED":0,"DISTANCE":405}
{"FL_DATE":"2000-01-16","OP_CARRIER_FL_NUM":488,"ORIGIN_CITY_NAME":"Knoxville, TN","DEST":"STL","DEST_CITY_NAME":"St. Louis, MO","CRS_DEP_TIME":1014,"DEP_TIME":1012,"WHEELS_ON":1026,"TAXI_IN":5,"CRS_ARR_TIME":1046,"ARR_TIME":1031,"CANCELLED":0,"DISTANCE":405}
{"FL_DATE":"2000-01-17","OP_CARRIER_FL_NUM":415,"ORIGIN_CITY_NAME":"Knoxville, TN","DEST":"STL","DEST_CITY_NAME":"St. Louis, MO","CRS_DEP_TIME":1602,"DEP_TIME":1802,"WHEELS_ON":1835,"TAXI_IN":7,"CRS_ARR_TIME":1634,"ARR_TIME":1842,"CANCELLED":0,"DISTANCE":405}
{"FL_DATE":"2000-01-17","OP_CARRIER_FL_NUM":647,"ORIGIN_CITY_NAME":"Knoxville, TN","DEST":"STL","DEST_CITY_NAME":"St. Louis, MO","CRS_DEP_TIME":728,"DEP_TIME":727,"WHEELS_ON":753,"TAXI_IN":6,"CRS_ARR_TIME":758,"ARR_TIME":759,"CANCELLED":0,"DISTANCE":405}
{"FL_DATE":"2000-01-18","OP_CARRIER_FL_NUM":415,"ORIGIN_CITY_NAME":"Knoxville, TN","DEST":"STL","DEST_CITY_NAME":"St. Louis, MO","CRS_DEP_TIME":1602,"DEP_TIME":1559,"WHEELS_ON":1644,"TAXI_IN":4,"CRS_ARR_TIME":1634,"ARR_TIME":1648,"CANCELLED":0,"DISTANCE":405}
{"FL_DATE":"2000-01-18","OP_CARRIER_FL_NUM":647,"ORIGIN_CITY_NAME":"Knoxville, TN","DEST":"STL","DEST_CITY_NAME":"St. Louis, MO","CRS_DEP_TIME":728,"DEP_TIME":726,"WHEELS_ON":812,"TAXI_IN":5,"CRS_ARR_TIME":758,"ARR_TIME":817,"CANCELLED":0,"DISTANCE":405}
{"FL_DATE":"2000-01-19","OP_CARRIER_FL_NUM":415,"ORIGIN_CITY_NAME":"Knoxville, TN","DEST":"STL","DEST_CITY_NAME":"St. Louis, MO","CRS_DEP_TIME":1602,"DEP_TIME":1601,"WHEELS_ON":1642,"TAXI_IN":9,"CRS_ARR_TIME":1634,"ARR_TIME":1651,"CANCELLED":0,"DISTANCE":405}
{"FL_DATE":"2000-01-19","OP_CARRIER_FL_NUM":647,"ORIGIN_CITY_NAME":"Knoxville, TN","DEST":"STL","DEST_CITY_NAME":"St. Louis, MO","CRS_DEP_TIME":728,"DEP_TIME":756,"WHEELS_ON":843,"TAXI_IN":4,"CRS_ARR_TIME":758,"ARR_TIME":847,"CANCELLED":0,"DISTANCE":405}
{"FL_DATE":"2000-01-20","OP_CARRIER_FL_NUM":415,"ORIGIN_CITY_NAME":"Knoxville, TN","DEST":"STL","DEST_CITY_NAME":"St. Louis, MO","CRS_DEP_TIME":1602,"DEP_TIME":1558,"WHEELS_ON":1640,"TAXI_IN":6,"CRS_ARR_TIME":1634,"ARR_TIME":1646,"CANCELLED":0,"DISTANCE":405}
{"FL_DATE":"2000-01-20","OP_CARRIER_FL_NUM":647,"ORIGIN_CITY_NAME":"Knoxville, TN","DEST":"STL","DEST_CITY_NAME":"St. Louis, MO","CRS_DEP_TIME":728,"DEP_TIME":728,"WHEELS_ON":802,"TAXI_IN":6,"CRS_ARR_TIME":758,"ARR_TIME":808,"CANCELLED":0,"DISTANCE":405}
{"FL_DATE":"2000-01-21","OP_CARRIER_FL_NUM":415,"ORIGIN_CITY_NAME":"Knoxville, TN","DEST":"STL","DEST_CITY_NAME":"St. Louis, MO","CRS_DEP_TIME":1602,"DEP_TIME":1601,"WHEELS_ON":1629,"TAXI_IN":5,"CRS_ARR_TIME":1634,"ARR_TIME":1634,"CANCELLED":0,"DISTANCE":405}
{"FL_DATE":"2000-01-21","OP_CARRIER_FL_NUM":647,"ORIGIN_CITY_NAME":"Knoxville, TN","DEST":"STL","DEST_CITY_NAME":"St. Louis, MO","CRS_DEP_TIME":728,"DEP_TIME":729,"WHEELS_ON":758,"TAXI_IN":10,"CRS_ARR_TIME":758,"ARR_TIME":808,"CANCELLED":0,"DISTANCE":405}
{"FL_DATE":"2000-01-22","OP_CARRIER_FL_NUM":415,"ORIGIN_CITY_NAME":"Knoxville, TN","DEST":"STL","DEST_CITY_NAME":"St. Louis, MO","CRS_DEP_TIME":1602,"DEP_TIME":1555,"WHEELS_ON":1642,"TAXI_IN":6,"CRS_ARR_TIME":1634,"ARR_TIME":1648,"CANCELLED":0,"DISTANCE":405}
{"FL_DATE":"2000-01-22","OP_CARRIER_FL_NUM":647,"ORIGIN_CITY_NAME":"Knoxville, TN","DEST":"STL","DEST_CITY_NAME":"St. Louis, MO","CRS_DEP_TIME":728,"DEP_TIME":726,"WHEELS_ON":823,"TAXI_IN":4,"CRS_ARR_TIME":758,"ARR_TIME":827,"CANCELLED":0,"DISTANCE":405}
{"FL_DATE":"2000-01-23","OP_CARRIER_FL_NUM":415,"ORIGIN_CITY_NAME":"Knoxville, TN","DEST":"STL","DEST_CITY_NAME":"St. Louis, MO","CRS_DEP_TIME":1602,"DEP_TIME":1601,"WHEELS_ON":1623,"TAXI_IN":5,"CRS_ARR_TIME":1634,"ARR_TIME":1628,"CANCELLED":0,"DISTANCE":405}
{"FL_DATE":"2000-01-23","OP_CARRIER_FL_NUM":488,"ORIGIN_CITY_NAME":"Knoxville, TN","DEST":"STL","DEST_CITY_NAME":"St. Louis, MO","CRS_DEP_TIME":1014,"DEP_TIME":1011,"WHEELS_ON":1031,"TAXI_IN":4,"CRS_ARR_TIME":1046,"ARR_TIME":1035,"CANCELLED":0,"DISTANCE":405}
{"FL_DATE":"2000-01-24","OP_CARRIER_FL_NUM":415,"ORIGIN_CITY_NAME":"Knoxville, TN","DEST":"STL","DEST_CITY_NAME":"St. Louis, MO","CRS_DEP_TIME":1602,"DEP_TIME":1602,"WHEELS_ON":1621,"TAXI_IN":5,"CRS_ARR_TIME":1634,"ARR_TIME":1626,"CANCELLED":0,"DISTANCE":405}
{"FL_DATE":"2000-01-24","OP_CARRIER_FL_NUM":647,"ORIGIN_CITY_NAME":"Knoxville, TN","DEST":"STL","DEST_CITY_NAME":"St. Louis, MO","CRS_DEP_TIME":728,"DEP_TIME":747,"WHEELS_ON":800,"TAXI_IN":3,"CRS_ARR_TIME":758,"ARR_TIME":803,"CANCELLED":0,"DISTANCE":405}
{"FL_DATE":"2000-01-25","OP_CARRIER_FL_NUM":415,"ORIGIN_CITY_NAME":"Knoxville, TN","DEST":"STL","DEST_CITY_NAME":"St. Louis, MO","CRS_DEP_TIME":1602,"DEP_TIME":1600,"WHEELS_ON":1626,"TAXI_IN":12,"CRS_ARR_TIME":1634,"ARR_TIME":1638,"CANCELLED":0,"DISTANCE":405}
{"FL_DATE":"2000-01-25","OP_CARRIER_FL_NUM":647,"ORIGIN_CITY_NAME":"Knoxville, TN","DEST":"STL","DEST_CITY_NAME":"St. Louis, MO","CRS_DEP_TIME":728,"DEP_TIME":726,"WHEELS_ON":751,"TAXI_IN":5,"CRS_ARR_TIME":758,"ARR_TIME":756,"CANCELLED":0,"DISTANCE":405}
{"FL_DATE":"2000-01-26","OP_CARRIER_FL_NUM":415,"ORIGIN_CITY_NAME":"Knoxville, TN","DEST":"STL","DEST_CITY_NAME":"St. Louis, MO","CRS_DEP_TIME":1602,"DEP_TIME":1558,"WHEELS_ON":1629,"TAXI_IN":7,"CRS_ARR_TIME":1634,"ARR_TIME":1636,"CANCELLED":0,"DISTANCE":405}
{"FL_DATE":"2000-01-26","OP_CARRIER_FL_NUM":647,"ORIGIN_CITY_NAME":"Knoxville, TN","DEST":"STL","DEST_CITY_NAME":"St. Louis, MO","CRS_DEP_TIME":728,"DEP_TIME":725,"WHEELS_ON":752,"TAXI_IN":5,"CRS_ARR_TIME":758,"ARR_TIME":757,"CANCELLED":0,"DISTANCE":405}
{"FL_DATE":"2000-01-27","OP_CARRIER_FL_NUM":415,"ORIGIN_CITY_NAME":"Knoxville, TN","DEST":"STL","DEST_CITY_NAME":"St. Louis, MO","CRS_DEP_TIME":1602,"DEP_TIME":1559,"WHEELS_ON":1627,"TAXI_IN":6,"CRS_ARR_TIME":1634,"ARR_TIME":1633,"CANCELLED":0,"DISTANCE":405}
{"FL_DATE":"2000-01-27","OP_CARRIER_FL_NUM":647,"ORIGIN_CITY_NAME":"Knoxville, TN","DEST":"STL","DEST_CITY_NAME":"St. Louis, MO","CRS_DEP_TIME":728,"DEP_TIME":727,"WHEELS_ON":746,"TAXI_IN":4,"CRS_ARR_TIME":758,"ARR_TIME":750,"CANCELLED":0,"DISTANCE":405}
{"FL_DATE":"2000-01-28","OP_CARRIER_FL_NUM":415,"ORIGIN_CITY_NAME":"Knoxville, TN","DEST":"STL","DEST_CITY_NAME":"St. Louis, MO","CRS_DEP_TIME":1602,"DEP_TIME":1559,"WHEELS_ON":1624,"TAXI_IN":5,"CRS_ARR_TIME":1634,"ARR_TIME":1629,"CANCELLED":0,"DISTANCE":405}
{"FL_DATE":"2000-01-28","OP_CARRIER_FL_NUM":647,"ORIGIN_CITY_NAME":"Knoxville, TN","DEST":"STL","DEST_CITY_NAME":"St. Louis, MO","CRS_DEP_TIME":728,"DEP_TIME":726,"WHEELS_ON":745,"TAXI_IN":11,"CRS_ARR_TIME":758,"ARR_TIME":756,"CANCELLED":0,"DISTANCE":405}
{"FL_DATE":"2000-01-29","OP_CARRIER_FL_NUM":415,"ORIGIN_CITY_NAME":"Knoxville, TN","DEST":"STL","DEST_CITY_NAME":"St. Louis, MO","CRS_DEP_TIME":1602,"DEP_TIME":1804,"WHEELS_ON":1825,"TAXI_IN":13,"CRS_ARR_TIME":1634,"ARR_TIME":1838,"CANCELLED":0,"DISTANCE":405}
{"FL_DATE":"2000-01-29","OP_CARRIER_FL_NUM":647,"ORIGIN_CITY_NAME":"Knoxville, TN","DEST":"STL","DEST_CITY_NAME":"St. Louis, MO","CRS_DEP_TIME":728,"DEP_TIME":728,"WHEELS_ON":801,"TAXI_IN":4,"CRS_ARR_TIME":758,"ARR_TIME":805,"CANCELLED":0,"DISTANCE":405}
{"FL_DATE":"2000-01-30","OP_CARRIER_FL_NUM":415,"ORIGIN_CITY_NAME":"Knoxville, TN","DEST":"STL","DEST_CITY_NAME":"St. Louis, MO","CRS_DEP_TIME":1602,"DEP_TIME":1610,"WHEELS_ON":1633,"TAXI_IN":9,"CRS_ARR_TIME":1634,"ARR_TIME":1642,"CANCELLED":0,"DISTANCE":405}
{"FL_DATE":"2000-01-30","OP_CARRIER_FL_NUM":488,"ORIGIN_CITY_NAME":"Knoxville, TN","DEST":"STL","DEST_CITY_NAME":"St. Louis, MO","CRS_DEP_TIME":1014,"DEP_TIME":1014,"WHEELS_ON":1036,"TAXI_IN":6,"CRS_ARR_TIME":1046,"ARR_TIME":1042,"CANCELLED":0,"DISTANCE":405}
{"FL_DATE":"2000-01-31","OP_CARRIER_FL_NUM":415,"ORIGIN_CITY_NAME":"Knoxville, TN","DEST":"STL","DEST_CITY_NAME":"St. Louis, MO","CRS_DEP_TIME":1602,"DEP_TIME":1559,"WHEELS_ON":1617,"TAXI_IN":8,"CRS_ARR_TIME":1634,"ARR_TIME":1625,"CANCELLED":0,"DISTANCE":405}
{"FL_DATE":"2000-01-31","OP_CARRIER_FL_NUM":647,"ORIGIN_CITY_NAME":"Knoxville, TN","DEST":"STL","DEST_CITY_NAME":"St. Louis, MO","CRS_DEP_TIME":728,"DEP_TIME":726,"WHEELS_ON":746,"TAXI_IN":9,"CRS_ARR_TIME":758,"ARR_TIME":755,"CANCELLED":0,"DISTANCE":405}
